LICENSE
MANIFEST.in
README.rst
setup.py
custom_delete_selected/__init__.py
custom_delete_selected/actions.py
custom_delete_selected/admin.py
django_custom_delete_selected.egg-info/PKG-INFO
django_custom_delete_selected.egg-info/SOURCES.txt
django_custom_delete_selected.egg-info/dependency_links.txt
django_custom_delete_selected.egg-info/requires.txt
django_custom_delete_selected.egg-info/top_level.txt