Metadata-Version: 1.1
Name: django-custom-delete-selected
Version: 0.1
Summary: Customization of delete_selected ModelAdmin action for post and pre operations.
Home-page: https://github.com/saippuakauppias/django-custom_delete_selected
Author: Denis Veselov
Author-email: progr.mail@gmail.com
License: ISC
Platform: UNKNOWN
Classifier: Development Status :: 5 - Production/Stable
Classifier: Framework :: Django
Classifier: Intended Audience :: Developers
Classifier: License :: OSI Approved :: ISC License (ISCL)
Classifier: Operating System :: OS Independent
Classifier: Programming Language :: Python
Classifier: Programming Language :: Python :: 2.6
Classifier: Programming Language :: Python :: 2.7
Classifier: Topic :: Internet :: WWW/HTTP
